ethtoken/__init__.py
ethtoken/abi.py
ethtoken/main.py
ethtoken-0.0.1a4.dist-info/METADATA
ethtoken-0.0.1a4.dist-info/WHEEL
ethtoken-0.0.1a4.dist-info/top_level.txt
ethtoken-0.0.1a4.dist-info/RECORD
