Metadata-Version: 2.1
Name: ethtoken
Version: 0.0.1a4
Summary: Ethereum EIP20 Token Interface
Home-page: https://github.com/carver/ethtoken.py
Author: Jason Carver
Author-email: ut96caarrs@snkmail.com
License: MIT
Keywords: ethereum erc20 token eip20 ICO ETH
Platform: UNKNOWN
Classifier: Development Status :: 2 - Pre-Alpha
Classifier: Intended Audience :: Developers
Classifier: License :: OSI Approved :: MIT License
Classifier: Natural Language :: English
Classifier: Programming Language :: Python :: 3
Classifier: Programming Language :: Python :: 3.5
Classifier: Programming Language :: Python :: 3.6
Requires-Dist: web3 (<5.0.0,>=4.0.0)
Provides-Extra: dev
Requires-Dist: bumpversion (<1,>=0.5.3); extra == 'dev'
Requires-Dist: pytest-xdist; extra == 'dev'
Requires-Dist: pytest-watch (<5,>=4.1.0); extra == 'dev'
Requires-Dist: wheel; extra == 'dev'
Requires-Dist: ipython; extra == 'dev'
Requires-Dist: pytest (==3.3.2); extra == 'dev'
Requires-Dist: tox (<3,>=2.9.1); extra == 'dev'
Requires-Dist: flake8 (==3.4.1); extra == 'dev'
Requires-Dist: isort (<5,>=4.2.15); extra == 'dev'
Requires-Dist: Sphinx (<2,>=1.6.5); extra == 'dev'
Requires-Dist: sphinx-rtd-theme (>=0.1.9); extra == 'dev'
Provides-Extra: doc
Requires-Dist: Sphinx (<2,>=1.6.5); extra == 'doc'
Requires-Dist: sphinx-rtd-theme (>=0.1.9); extra == 'doc'
Provides-Extra: lint
Requires-Dist: flake8 (==3.4.1); extra == 'lint'
Requires-Dist: isort (<5,>=4.2.15); extra == 'lint'
Provides-Extra: test
Requires-Dist: pytest (==3.3.2); extra == 'test'
Requires-Dist: tox (<3,>=2.9.1); extra == 'test'
